[
  {
    "id": "kovo_20251220_HEUNGKUK PINKSPIDERS_PEPPER SAVINGS BANK",
    "title": "[배구] HEUNGKUK PINKSPIDERS vs PEPPER SAVINGS BANK",
    "image": "/culture/images/volleyball_poster.png",
    "date": "2025-12-20 14:00",
    "venue": "인천 삼산월드체육관",
    "link": "https://kovo.co.kr/tickets/single",
    "region": "incheon",
    "genre": "volleyball"
  },
  {
    "id": "kovo_20251215_HYUNDAI CAPITAL_OK SAVINGS BANK",
    "title": "[배구] HYUNDAI CAPITAL vs OK SAVINGS BANK",
    "image": "/culture/images/volleyball_poster.png",
    "date": "2025-12-15 11:00",
    "venue": "12.20(토) 14:00",
    "link": "https://kovo.co.kr/tickets/single",
    "region": "etc",
    "genre": "volleyball"
  },
  {
    "id": "kovo_20251220_HYUNDAI CAPITAL_OK SAVINGS BANK",
    "title": "[배구] HYUNDAI CAPITAL vs OK SAVINGS BANK",
    "image": "/culture/images/volleyball_poster.png",
    "date": "2025-12-20 14:00",
    "venue": "천안 유관순체육관",
    "link": "https://kovo.co.kr/tickets/single",
    "region": "etc",
    "genre": "volleyball"
  },
  {
    "id": "kovo_20251215_WOORICARD_KB STARS",
    "title": "[배구] WOORICARD vs KB STARS",
    "image": "/culture/images/volleyball_poster.png",
    "date": "2025-12-15 11:00",
    "venue": "12.21(일) 14:00",
    "link": "https://kovo.co.kr/tickets/single",
    "region": "etc",
    "genre": "volleyball"
  },
  {
    "id": "kovo_20251221_WOORICARD_KB STARS",
    "title": "[배구] WOORICARD vs KB STARS",
    "image": "/culture/images/volleyball_poster.png",
    "date": "2025-12-21 14:00",
    "venue": "장충체육관",
    "link": "https://kovo.co.kr/tickets/single",
    "region": "seoul",
    "genre": "volleyball"
  },
  {
    "id": "kovo_20251216_INDUSTRIAL BANK OF KOREA_HYUNDAI E&C",
    "title": "[배구] INDUSTRIAL BANK OF KOREA vs HYUNDAI E&C",
    "image": "/culture/images/volleyball_poster.png",
    "date": "2025-12-16 11:00",
    "venue": "12.21(일) 16:00",
    "link": "https://kovo.co.kr/tickets/single",
    "region": "etc",
    "genre": "volleyball"
  },
  {
    "id": "kovo_20251221_INDUSTRIAL BANK OF KOREA_HYUNDAI E&C",
    "title": "[배구] INDUSTRIAL BANK OF KOREA vs HYUNDAI E&C",
    "image": "/culture/images/volleyball_poster.png",
    "date": "2025-12-21 16:00",
    "venue": "화성종합경기타운 실내체육관",
    "link": "https://kovo.co.kr/tickets/single",
    "region": "gyeonggi",
    "genre": "volleyball"
  },
  {
    "id": "kovo_20251216_GS CALTEX_KOREA EXPRESSWAY",
    "title": "[배구] GS CALTEX vs KOREA EXPRESSWAY",
    "image": "/culture/images/volleyball_poster.png",
    "date": "2025-12-16 11:00",
    "venue": "12.23(화) 19:00",
    "link": "https://kovo.co.kr/tickets/single",
    "region": "etc",
    "genre": "volleyball"
  },
  {
    "id": "kovo_20251223_GS CALTEX_KOREA EXPRESSWAY",
    "title": "[배구] GS CALTEX vs KOREA EXPRESSWAY",
    "image": "/culture/images/volleyball_poster.png",
    "date": "2025-12-23 19:00",
    "venue": "장충체육관",
    "link": "https://kovo.co.kr/tickets/single",
    "region": "seoul",
    "genre": "volleyball"
  },
  {
    "id": "kovo_20251218_KEPCO_SAMSUNG BLUEFANGS",
    "title": "[배구] KEPCO vs SAMSUNG BLUEFANGS",
    "image": "/culture/images/volleyball_poster.png",
    "date": "2025-12-18 15:00",
    "venue": "12.23(화) 19:00",
    "link": "https://kovo.co.kr/tickets/single",
    "region": "etc",
    "genre": "volleyball"
  },
  {
    "id": "kovo_20251223_KEPCO_SAMSUNG BLUEFANGS",
    "title": "[배구] KEPCO vs SAMSUNG BLUEFANGS",
    "image": "/culture/images/volleyball_poster.png",
    "date": "2025-12-23 19:00",
    "venue": "수원 실내체육관",
    "link": "https://kovo.co.kr/tickets/single",
    "region": "gyeonggi",
    "genre": "volleyball"
  },
  {
    "id": "kovo_20251218_HEUNGKUK PINKSPIDERS_INDUSTRIAL BANK OF KOREA",
    "title": "[배구] HEUNGKUK PINKSPIDERS vs INDUSTRIAL BANK OF KOREA",
    "image": "/culture/images/volleyball_poster.png",
    "date": "2025-12-18 11:00",
    "venue": "12.24(수) 19:00",
    "link": "https://kovo.co.kr/tickets/single",
    "region": "etc",
    "genre": "volleyball"
  },
  {
    "id": "kovo_20251224_HEUNGKUK PINKSPIDERS_INDUSTRIAL BANK OF KOREA",
    "title": "[배구] HEUNGKUK PINKSPIDERS vs INDUSTRIAL BANK OF KOREA",
    "image": "/culture/images/volleyball_poster.png",
    "date": "2025-12-24 19:00",
    "venue": "인천 삼산월드체육관",
    "link": "https://kovo.co.kr/tickets/single",
    "region": "incheon",
    "genre": "volleyball"
  },
  {
    "id": "kovo_20251219_HYUNDAI CAPITAL_WOORICARD",
    "title": "[배구] HYUNDAI CAPITAL vs WOORICARD",
    "image": "/culture/images/volleyball_poster.png",
    "date": "2025-12-19 11:00",
    "venue": "12.24(수) 19:00",
    "link": "https://kovo.co.kr/tickets/single",
    "region": "etc",
    "genre": "volleyball"
  },
  {
    "id": "kovo_20251224_HYUNDAI CAPITAL_WOORICARD",
    "title": "[배구] HYUNDAI CAPITAL vs WOORICARD",
    "image": "/culture/images/volleyball_poster.png",
    "date": "2025-12-24 19:00",
    "venue": "천안 유관순체육관",
    "link": "https://kovo.co.kr/tickets/single",
    "region": "etc",
    "genre": "volleyball"
  },
  {
    "id": "kovo_20251219_KB STARS_KOREAN AIR",
    "title": "[배구] KB STARS vs KOREAN AIR",
    "image": "/culture/images/volleyball_poster.png",
    "date": "2025-12-19 11:00",
    "venue": "12.25(목) 14:00",
    "link": "https://kovo.co.kr/tickets/single",
    "region": "etc",
    "genre": "volleyball"
  },
  {
    "id": "kovo_20251225_KB STARS_KOREAN AIR",
    "title": "[배구] KB STARS vs KOREAN AIR",
    "image": "/culture/images/volleyball_poster.png",
    "date": "2025-12-25 14:00",
    "venue": "의정부 경민대학교 기념관(체육관)",
    "link": "https://kovo.co.kr/tickets/single",
    "region": "gyeonggi",
    "genre": "volleyball"
  },
  {
    "id": "kovo_20251220_HYUNDAI E&C_JUNG KWAN JANG",
    "title": "[배구] HYUNDAI E&C vs JUNG KWAN JANG",
    "image": "/culture/images/volleyball_poster.png",
    "date": "2025-12-20 11:00",
    "venue": "12.25(목) 16:00",
    "link": "https://kovo.co.kr/tickets/single",
    "region": "etc",
    "genre": "volleyball"
  },
  {
    "id": "kovo_20251225_HYUNDAI E&C_JUNG KWAN JANG",
    "title": "[배구] HYUNDAI E&C vs JUNG KWAN JANG",
    "image": "/culture/images/volleyball_poster.png",
    "date": "2025-12-25 16:00",
    "venue": "수원실내체육관",
    "link": "https://kovo.co.kr/tickets/single",
    "region": "gyeonggi",
    "genre": "volleyball"
  },
  {
    "id": "kovo_20251220_SAMSUNG BLUEFANGS_OK SAVINGS BANK",
    "title": "[배구] SAMSUNG BLUEFANGS vs OK SAVINGS BANK",
    "image": "/culture/images/volleyball_poster.png",
    "date": "2025-12-20 11:00",
    "venue": "12.26(금) 19:00",
    "link": "https://kovo.co.kr/tickets/single",
    "region": "etc",
    "genre": "volleyball"
  },
  {
    "id": "kovo_20251226_SAMSUNG BLUEFANGS_OK SAVINGS BANK",
    "title": "[배구] SAMSUNG BLUEFANGS vs OK SAVINGS BANK",
    "image": "/culture/images/volleyball_poster.png",
    "date": "2025-12-26 19:00",
    "venue": "대전 충무체육관",
    "link": "https://kovo.co.kr/tickets/single",
    "region": "etc",
    "genre": "volleyball"
  },
  {
    "id": "kovo_20251221_KOREA EXPRESSWAY_PEPPER SAVINGS BANK",
    "title": "[배구] KOREA EXPRESSWAY vs PEPPER SAVINGS BANK",
    "image": "/culture/images/volleyball_poster.png",
    "date": "2025-12-21 11:00",
    "venue": "12.26(금) 19:00",
    "link": "https://kovo.co.kr/tickets/single",
    "region": "etc",
    "genre": "volleyball"
  },
  {
    "id": "kovo_20251226_KOREA EXPRESSWAY_PEPPER SAVINGS BANK",
    "title": "[배구] KOREA EXPRESSWAY vs PEPPER SAVINGS BANK",
    "image": "/culture/images/volleyball_poster.png",
    "date": "2025-12-26 19:00",
    "venue": "김천실내체육관",
    "link": "https://kovo.co.kr/tickets/single",
    "region": "etc",
    "genre": "volleyball"
  },
  {
    "id": "kovo_20251221_KEPCO_HYUNDAI CAPITAL",
    "title": "[배구] KEPCO vs HYUNDAI CAPITAL",
    "image": "/culture/images/volleyball_poster.png",
    "date": "2025-12-21 11:00",
    "venue": "12.27(토) 14:00",
    "link": "https://kovo.co.kr/tickets/single",
    "region": "etc",
    "genre": "volleyball"
  },
  {
    "id": "kovo_20251227_KEPCO_HYUNDAI CAPITAL",
    "title": "[배구] KEPCO vs HYUNDAI CAPITAL",
    "image": "/culture/images/volleyball_poster.png",
    "date": "2025-12-27 14:00",
    "venue": "수원 실내체육관",
    "link": "https://kovo.co.kr/tickets/single",
    "region": "gyeonggi",
    "genre": "volleyball"
  },
  {
    "id": "kovo_20251222_GS CALTEX_HEUNGKUK PINKSPIDERS",
    "title": "[배구] GS CALTEX vs HEUNGKUK PINKSPIDERS",
    "image": "/culture/images/volleyball_poster.png",
    "date": "2025-12-22 11:00",
    "venue": "12.27(토) 16:00",
    "link": "https://kovo.co.kr/tickets/single",
    "region": "etc",
    "genre": "volleyball"
  },
  {
    "id": "kovo_20251227_GS CALTEX_HEUNGKUK PINKSPIDERS",
    "title": "[배구] GS CALTEX vs HEUNGKUK PINKSPIDERS",
    "image": "/culture/images/volleyball_poster.png",
    "date": "2025-12-27 16:00",
    "venue": "장충체육관",
    "link": "https://kovo.co.kr/tickets/single",
    "region": "seoul",
    "genre": "volleyball"
  },
  {
    "id": "kovo_20251222_WOORICARD_KOREAN AIR",
    "title": "[배구] WOORICARD vs KOREAN AIR",
    "image": "/culture/images/volleyball_poster.png",
    "date": "2025-12-22 15:00",
    "venue": "12.28(일) 14:00",
    "link": "https://kovo.co.kr/tickets/single",
    "region": "etc",
    "genre": "volleyball"
  },
  {
    "id": "kovo_20251228_WOORICARD_KOREAN AIR",
    "title": "[배구] WOORICARD vs KOREAN AIR",
    "image": "/culture/images/volleyball_poster.png",
    "date": "2025-12-28 14:00",
    "venue": "장충체육관",
    "link": "https://kovo.co.kr/tickets/single",
    "region": "seoul",
    "genre": "volleyball"
  },
  {
    "id": "kovo_20251223_INDUSTRIAL BANK OF KOREA_JUNG KWAN JANG",
    "title": "[배구] INDUSTRIAL BANK OF KOREA vs JUNG KWAN JANG",
    "image": "/culture/images/volleyball_poster.png",
    "date": "2025-12-23 11:00",
    "venue": "12.28(일) 16:00",
    "link": "https://kovo.co.kr/tickets/single",
    "region": "etc",
    "genre": "volleyball"
  },
  {
    "id": "kovo_20251228_INDUSTRIAL BANK OF KOREA_JUNG KWAN JANG",
    "title": "[배구] INDUSTRIAL BANK OF KOREA vs JUNG KWAN JANG",
    "image": "/culture/images/volleyball_poster.png",
    "date": "2025-12-28 16:00",
    "venue": "화성종합경기타운 실내체육관",
    "link": "https://kovo.co.kr/tickets/single",
    "region": "gyeonggi",
    "genre": "volleyball"
  },
  {
    "id": "kovo_20251223_PEPPER SAVINGS BANK_GS CALTEX",
    "title": "[배구] PEPPER SAVINGS BANK vs GS CALTEX",
    "image": "/culture/images/volleyball_poster.png",
    "date": "2025-12-23 11:00",
    "venue": "12.30(화) 19:00",
    "link": "https://kovo.co.kr/tickets/single",
    "region": "etc",
    "genre": "volleyball"
  },
  {
    "id": "kovo_20251230_PEPPER SAVINGS BANK_GS CALTEX",
    "title": "[배구] PEPPER SAVINGS BANK vs GS CALTEX",
    "image": "/culture/images/volleyball_poster.png",
    "date": "2025-12-30 19:00",
    "venue": "페퍼스타디움",
    "link": "https://kovo.co.kr/tickets/single",
    "region": "etc",
    "genre": "volleyball"
  },
  {
    "id": "kovo_20251225_OK SAVINGS BANK_KEPCO",
    "title": "[배구] OK SAVINGS BANK vs KEPCO",
    "image": "/culture/images/volleyball_poster.png",
    "date": "2025-12-25 11:00",
    "venue": "12.30(화) 19:00",
    "link": "https://kovo.co.kr/tickets/single",
    "region": "etc",
    "genre": "volleyball"
  },
  {
    "id": "kovo_20251230_OK SAVINGS BANK_KEPCO",
    "title": "[배구] OK SAVINGS BANK vs KEPCO",
    "image": "/culture/images/volleyball_poster.png",
    "date": "2025-12-30 19:00",
    "venue": "부산강서실내체육관",
    "link": "https://kovo.co.kr/tickets/single",
    "region": "etc",
    "genre": "volleyball"
  },
  {
    "id": "kovo_20251225_HYUNDAI CAPITAL_KB STARS",
    "title": "[배구] HYUNDAI CAPITAL vs KB STARS",
    "image": "/culture/images/volleyball_poster.png",
    "date": "2025-12-25 11:00",
    "venue": "12.31(수) 19:00",
    "link": "https://kovo.co.kr/tickets/single",
    "region": "etc",
    "genre": "volleyball"
  },
  {
    "id": "kovo_20251231_HYUNDAI CAPITAL_KB STARS",
    "title": "[배구] HYUNDAI CAPITAL vs KB STARS",
    "image": "/culture/images/volleyball_poster.png",
    "date": "2025-12-31 19:00",
    "venue": "천안 유관순체육관",
    "link": "https://kovo.co.kr/tickets/single",
    "region": "etc",
    "genre": "volleyball"
  },
  {
    "id": "kovo_20251226_HEUNGKUK PINKSPIDERS_HYUNDAI E&C",
    "title": "[배구] HEUNGKUK PINKSPIDERS vs HYUNDAI E&C",
    "image": "/culture/images/volleyball_poster.png",
    "date": "2025-12-26 11:00",
    "venue": "12.31(수) 19:00",
    "link": "https://kovo.co.kr/tickets/single",
    "region": "etc",
    "genre": "volleyball"
  },
  {
    "id": "kovo_20251231_HEUNGKUK PINKSPIDERS_HYUNDAI E&C",
    "title": "[배구] HEUNGKUK PINKSPIDERS vs HYUNDAI E&C",
    "image": "/culture/images/volleyball_poster.png",
    "date": "2025-12-31 19:00",
    "venue": "인천 삼산월드체육관",
    "link": "https://kovo.co.kr/tickets/single",
    "region": "incheon",
    "genre": "volleyball"
  },
  {
    "id": "kovo_20251226_KOREAN AIR_SAMSUNG BLUEFANGS",
    "title": "[배구] KOREAN AIR vs SAMSUNG BLUEFANGS",
    "image": "/culture/images/volleyball_poster.png",
    "date": "2025-12-26 11:00",
    "venue": "01.01(목) 14:00",
    "link": "https://kovo.co.kr/tickets/single",
    "region": "etc",
    "genre": "volleyball"
  },
  {
    "id": "kovo_20260101_KOREAN AIR_SAMSUNG BLUEFANGS",
    "title": "[배구] KOREAN AIR vs SAMSUNG BLUEFANGS",
    "image": "/culture/images/volleyball_poster.png",
    "date": "2026-01-01 14:00",
    "venue": "인천 계양체육관",
    "link": "https://kovo.co.kr/tickets/single",
    "region": "incheon",
    "genre": "volleyball"
  },
  {
    "id": "kovo_20251227_JUNG KWAN JANG_KOREA EXPRESSWAY",
    "title": "[배구] JUNG KWAN JANG vs KOREA EXPRESSWAY",
    "image": "/culture/images/volleyball_poster.png",
    "date": "2025-12-27 11:00",
    "venue": "01.01(목) 16:00",
    "link": "https://kovo.co.kr/tickets/single",
    "region": "etc",
    "genre": "volleyball"
  },
  {
    "id": "kovo_20260101_JUNG KWAN JANG_KOREA EXPRESSWAY",
    "title": "[배구] JUNG KWAN JANG vs KOREA EXPRESSWAY",
    "image": "/culture/images/volleyball_poster.png",
    "date": "2026-01-01 16:00",
    "venue": "대전 충무체육관",
    "link": "https://kovo.co.kr/tickets/single",
    "region": "etc",
    "genre": "volleyball"
  },
  {
    "id": "kovo_20251227_OK SAVINGS BANK_WOORICARD",
    "title": "[배구] OK SAVINGS BANK vs WOORICARD",
    "image": "/culture/images/volleyball_poster.png",
    "date": "2025-12-27 11:00",
    "venue": "01.02(금) 19:00",
    "link": "https://kovo.co.kr/tickets/single",
    "region": "etc",
    "genre": "volleyball"
  },
  {
    "id": "kovo_20260102_OK SAVINGS BANK_WOORICARD",
    "title": "[배구] OK SAVINGS BANK vs WOORICARD",
    "image": "/culture/images/volleyball_poster.png",
    "date": "2026-01-02 19:00",
    "venue": "부산강서실내체육관",
    "link": "https://kovo.co.kr/tickets/single",
    "region": "etc",
    "genre": "volleyball"
  },
  {
    "id": "kovo_20251228_PEPPER SAVINGS BANK_INDUSTRIAL BANK OF KOREA",
    "title": "[배구] PEPPER SAVINGS BANK vs INDUSTRIAL BANK OF KOREA",
    "image": "/culture/images/volleyball_poster.png",
    "date": "2025-12-28 11:00",
    "venue": "01.02(금) 19:00",
    "link": "https://kovo.co.kr/tickets/single",
    "region": "etc",
    "genre": "volleyball"
  },
  {
    "id": "kovo_20260102_PEPPER SAVINGS BANK_INDUSTRIAL BANK OF KOREA",
    "title": "[배구] PEPPER SAVINGS BANK vs INDUSTRIAL BANK OF KOREA",
    "image": "/culture/images/volleyball_poster.png",
    "date": "2026-01-02 19:00",
    "venue": "페퍼스타디움",
    "link": "https://kovo.co.kr/tickets/single",
    "region": "etc",
    "genre": "volleyball"
  },
  {
    "id": "kovo_20251228_KB STARS_KEPCO",
    "title": "[배구] KB STARS vs KEPCO",
    "image": "/culture/images/volleyball_poster.png",
    "date": "2025-12-28 11:00",
    "venue": "01.03(토) 14:00",
    "link": "https://kovo.co.kr/tickets/single",
    "region": "etc",
    "genre": "volleyball"
  },
  {
    "id": "kovo_20260103_KB STARS_KEPCO",
    "title": "[배구] KB STARS vs KEPCO",
    "image": "/culture/images/volleyball_poster.png",
    "date": "2026-01-03 14:00",
    "venue": "의정부 경민대학교 기념관(체육관)",
    "link": "https://kovo.co.kr/tickets/single",
    "region": "gyeonggi",
    "genre": "volleyball"
  },
  {
    "id": "kovo_20251229_HYUNDAI E&C_GS CALTEX",
    "title": "[배구] HYUNDAI E&C vs GS CALTEX",
    "image": "/culture/images/volleyball_poster.png",
    "date": "2025-12-29 11:00",
    "venue": "01.03(토) 16:00",
    "link": "https://kovo.co.kr/tickets/single",
    "region": "etc",
    "genre": "volleyball"
  },
  {
    "id": "kovo_20260103_HYUNDAI E&C_GS CALTEX",
    "title": "[배구] HYUNDAI E&C vs GS CALTEX",
    "image": "/culture/images/volleyball_poster.png",
    "date": "2026-01-03 16:00",
    "venue": "수원실내체육관",
    "link": "https://kovo.co.kr/tickets/single",
    "region": "gyeonggi",
    "genre": "volleyball"
  },
  {
    "id": "kovo_20251229_KOREAN AIR_HYUNDAI CAPITAL",
    "title": "[배구] KOREAN AIR vs HYUNDAI CAPITAL",
    "image": "/culture/images/volleyball_poster.png",
    "date": "2025-12-29 11:00",
    "venue": "01.04(일) 14:00",
    "link": "https://kovo.co.kr/tickets/single",
    "region": "etc",
    "genre": "volleyball"
  },
  {
    "id": "kovo_20260104_KOREAN AIR_HYUNDAI CAPITAL",
    "title": "[배구] KOREAN AIR vs HYUNDAI CAPITAL",
    "image": "/culture/images/volleyball_poster.png",
    "date": "2026-01-04 14:00",
    "venue": "인천 계양체육관",
    "link": "https://kovo.co.kr/tickets/single",
    "region": "incheon",
    "genre": "volleyball"
  },
  {
    "id": "kovo_20251230_JUNG KWAN JANG_HEUNGKUK PINKSPIDERS",
    "title": "[배구] JUNG KWAN JANG vs HEUNGKUK PINKSPIDERS",
    "image": "/culture/images/volleyball_poster.png",
    "date": "2025-12-30 11:00",
    "venue": "01.04(일) 16:00",
    "link": "https://kovo.co.kr/tickets/single",
    "region": "etc",
    "genre": "volleyball"
  },
  {
    "id": "kovo_20260104_JUNG KWAN JANG_HEUNGKUK PINKSPIDERS",
    "title": "[배구] JUNG KWAN JANG vs HEUNGKUK PINKSPIDERS",
    "image": "/culture/images/volleyball_poster.png",
    "date": "2026-01-04 16:00",
    "venue": "대전 충무체육관",
    "link": "https://kovo.co.kr/tickets/single",
    "region": "etc",
    "genre": "volleyball"
  },
  {
    "id": "kovo_20251230_GS CALTEX_PEPPER SAVINGS BANK",
    "title": "[배구] GS CALTEX vs PEPPER SAVINGS BANK",
    "image": "/culture/images/volleyball_poster.png",
    "date": "2025-12-30 11:00",
    "venue": "01.06(화) 19:00",
    "link": "https://kovo.co.kr/tickets/single",
    "region": "etc",
    "genre": "volleyball"
  },
  {
    "id": "kovo_20260106_GS CALTEX_PEPPER SAVINGS BANK",
    "title": "[배구] GS CALTEX vs PEPPER SAVINGS BANK",
    "image": "/culture/images/volleyball_poster.png",
    "date": "2026-01-06 19:00",
    "venue": "장충체육관",
    "link": "https://kovo.co.kr/tickets/single",
    "region": "seoul",
    "genre": "volleyball"
  },
  {
    "id": "kovo_20260101_KEPCO_OK SAVINGS BANK",
    "title": "[배구] KEPCO vs OK SAVINGS BANK",
    "image": "/culture/images/volleyball_poster.png",
    "date": "2026-01-01 15:00",
    "venue": "01.06(화) 19:00",
    "link": "https://kovo.co.kr/tickets/single",
    "region": "etc",
    "genre": "volleyball"
  },
  {
    "id": "kovo_20260106_KEPCO_OK SAVINGS BANK",
    "title": "[배구] KEPCO vs OK SAVINGS BANK",
    "image": "/culture/images/volleyball_poster.png",
    "date": "2026-01-06 19:00",
    "venue": "수원 실내체육관",
    "link": "https://kovo.co.kr/tickets/single",
    "region": "gyeonggi",
    "genre": "volleyball"
  },
  {
    "id": "kovo_20260101_KOREA EXPRESSWAY_HYUNDAI E&C",
    "title": "[배구] KOREA EXPRESSWAY vs HYUNDAI E&C",
    "image": "/culture/images/volleyball_poster.png",
    "date": "2026-01-01 11:00",
    "venue": "01.07(수) 19:00",
    "link": "https://kovo.co.kr/tickets/single",
    "region": "etc",
    "genre": "volleyball"
  },
  {
    "id": "kovo_20260107_KOREA EXPRESSWAY_HYUNDAI E&C",
    "title": "[배구] KOREA EXPRESSWAY vs HYUNDAI E&C",
    "image": "/culture/images/volleyball_poster.png",
    "date": "2026-01-07 19:00",
    "venue": "김천실내체육관",
    "link": "https://kovo.co.kr/tickets/single",
    "region": "etc",
    "genre": "volleyball"
  },
  {
    "id": "kovo_20260102_SAMSUNG BLUEFANGS_KB STARS",
    "title": "[배구] SAMSUNG BLUEFANGS vs KB STARS",
    "image": "/culture/images/volleyball_poster.png",
    "date": "2026-01-02 11:00",
    "venue": "01.07(수) 19:00",
    "link": "https://kovo.co.kr/tickets/single",
    "region": "etc",
    "genre": "volleyball"
  },
  {
    "id": "kovo_20260107_SAMSUNG BLUEFANGS_KB STARS",
    "title": "[배구] SAMSUNG BLUEFANGS vs KB STARS",
    "image": "/culture/images/volleyball_poster.png",
    "date": "2026-01-07 19:00",
    "venue": "대전 충무체육관",
    "link": "https://kovo.co.kr/tickets/single",
    "region": "etc",
    "genre": "volleyball"
  },
  {
    "id": "kovo_20260102_WOORICARD_KOREAN AIR",
    "title": "[배구] WOORICARD vs KOREAN AIR",
    "image": "/culture/images/volleyball_poster.png",
    "date": "2026-01-02 11:00",
    "venue": "01.08(목) 19:00",
    "link": "https://kovo.co.kr/tickets/single",
    "region": "etc",
    "genre": "volleyball"
  },
  {
    "id": "kovo_20260108_WOORICARD_KOREAN AIR",
    "title": "[배구] WOORICARD vs KOREAN AIR",
    "image": "/culture/images/volleyball_poster.png",
    "date": "2026-01-08 19:00",
    "venue": "장충체육관",
    "link": "https://kovo.co.kr/tickets/single",
    "region": "seoul",
    "genre": "volleyball"
  },
  {
    "id": "kovo_20260103_INDUSTRIAL BANK OF KOREA_JUNG KWAN JANG",
    "title": "[배구] INDUSTRIAL BANK OF KOREA vs JUNG KWAN JANG",
    "image": "/culture/images/volleyball_poster.png",
    "date": "2026-01-03 11:00",
    "venue": "01.08(목) 19:00",
    "link": "https://kovo.co.kr/tickets/single",
    "region": "etc",
    "genre": "volleyball"
  },
  {
    "id": "kovo_20260108_INDUSTRIAL BANK OF KOREA_JUNG KWAN JANG",
    "title": "[배구] INDUSTRIAL BANK OF KOREA vs JUNG KWAN JANG",
    "image": "/culture/images/volleyball_poster.png",
    "date": "2026-01-08 19:00",
    "venue": "화성종합경기타운 실내체육관",
    "link": "https://kovo.co.kr/tickets/single",
    "region": "gyeonggi",
    "genre": "volleyball"
  },
  {
    "id": "kovo_20260103_OK SAVINGS BANK_HYUNDAI CAPITAL",
    "title": "[배구] OK SAVINGS BANK vs HYUNDAI CAPITAL",
    "image": "/culture/images/volleyball_poster.png",
    "date": "2026-01-03 11:00",
    "venue": "01.09(금) 19:00",
    "link": "https://kovo.co.kr/tickets/single",
    "region": "etc",
    "genre": "volleyball"
  },
  {
    "id": "kovo_20260109_OK SAVINGS BANK_HYUNDAI CAPITAL",
    "title": "[배구] OK SAVINGS BANK vs HYUNDAI CAPITAL",
    "image": "/culture/images/volleyball_poster.png",
    "date": "2026-01-09 19:00",
    "venue": "부산강서실내체육관",
    "link": "https://kovo.co.kr/tickets/single",
    "region": "etc",
    "genre": "volleyball"
  },
  {
    "id": "kovo_20260104_PEPPER SAVINGS BANK_HEUNGKUK PINKSPIDERS",
    "title": "[배구] PEPPER SAVINGS BANK vs HEUNGKUK PINKSPIDERS",
    "image": "/culture/images/volleyball_poster.png",
    "date": "2026-01-04 11:00",
    "venue": "01.09(금) 19:00",
    "link": "https://kovo.co.kr/tickets/single",
    "region": "etc",
    "genre": "volleyball"
  },
  {
    "id": "kovo_20260109_PEPPER SAVINGS BANK_HEUNGKUK PINKSPIDERS",
    "title": "[배구] PEPPER SAVINGS BANK vs HEUNGKUK PINKSPIDERS",
    "image": "/culture/images/volleyball_poster.png",
    "date": "2026-01-09 19:00",
    "venue": "페퍼스타디움",
    "link": "https://kovo.co.kr/tickets/single",
    "region": "etc",
    "genre": "volleyball"
  },
  {
    "id": "kovo_20260104_SAMSUNG BLUEFANGS_KEPCO",
    "title": "[배구] SAMSUNG BLUEFANGS vs KEPCO",
    "image": "/culture/images/volleyball_poster.png",
    "date": "2026-01-04 11:00",
    "venue": "01.10(토) 14:00",
    "link": "https://kovo.co.kr/tickets/single",
    "region": "etc",
    "genre": "volleyball"
  },
  {
    "id": "kovo_20260110_SAMSUNG BLUEFANGS_KEPCO",
    "title": "[배구] SAMSUNG BLUEFANGS vs KEPCO",
    "image": "/culture/images/volleyball_poster.png",
    "date": "2026-01-10 14:00",
    "venue": "대전 충무체육관",
    "link": "https://kovo.co.kr/tickets/single",
    "region": "etc",
    "genre": "volleyball"
  },
  {
    "id": "kovo_20260105_KOREA EXPRESSWAY_GS CALTEX",
    "title": "[배구] KOREA EXPRESSWAY vs GS CALTEX",
    "image": "/culture/images/volleyball_poster.png",
    "date": "2026-01-05 11:00",
    "venue": "01.10(토) 16:00",
    "link": "https://kovo.co.kr/tickets/single",
    "region": "etc",
    "genre": "volleyball"
  },
  {
    "id": "kovo_20260110_KOREA EXPRESSWAY_GS CALTEX",
    "title": "[배구] KOREA EXPRESSWAY vs GS CALTEX",
    "image": "/culture/images/volleyball_poster.png",
    "date": "2026-01-10 16:00",
    "venue": "김천실내체육관",
    "link": "https://kovo.co.kr/tickets/single",
    "region": "etc",
    "genre": "volleyball"
  },
  {
    "id": "kovo_20260105_WOORICARD_KB STARS",
    "title": "[배구] WOORICARD vs KB STARS",
    "image": "/culture/images/volleyball_poster.png",
    "date": "2026-01-05 11:00",
    "venue": "01.11(일) 14:00",
    "link": "https://kovo.co.kr/tickets/single",
    "region": "etc",
    "genre": "volleyball"
  },
  {
    "id": "kovo_20260111_WOORICARD_KB STARS",
    "title": "[배구] WOORICARD vs KB STARS",
    "image": "/culture/images/volleyball_poster.png",
    "date": "2026-01-11 14:00",
    "venue": "장충체육관",
    "link": "https://kovo.co.kr/tickets/single",
    "region": "seoul",
    "genre": "volleyball"
  },
  {
    "id": "kovo_20260106_INDUSTRIAL BANK OF KOREA_HYUNDAI E&C",
    "title": "[배구] INDUSTRIAL BANK OF KOREA vs HYUNDAI E&C",
    "image": "/culture/images/volleyball_poster.png",
    "date": "2026-01-06 11:00",
    "venue": "01.11(일) 16:00",
    "link": "https://kovo.co.kr/tickets/single",
    "region": "etc",
    "genre": "volleyball"
  },
  {
    "id": "kovo_20260111_INDUSTRIAL BANK OF KOREA_HYUNDAI E&C",
    "title": "[배구] INDUSTRIAL BANK OF KOREA vs HYUNDAI E&C",
    "image": "/culture/images/volleyball_poster.png",
    "date": "2026-01-11 16:00",
    "venue": "화성종합경기타운 실내체육관",
    "link": "https://kovo.co.kr/tickets/single",
    "region": "gyeonggi",
    "genre": "volleyball"
  },
  {
    "id": "kovo_20260106_KOREAN AIR_OK SAVINGS BANK",
    "title": "[배구] KOREAN AIR vs OK SAVINGS BANK",
    "image": "/culture/images/volleyball_poster.png",
    "date": "2026-01-06 11:00",
    "venue": "01.13(화) 19:00",
    "link": "https://kovo.co.kr/tickets/single",
    "region": "etc",
    "genre": "volleyball"
  },
  {
    "id": "kovo_20260113_KOREAN AIR_OK SAVINGS BANK",
    "title": "[배구] KOREAN AIR vs OK SAVINGS BANK",
    "image": "/culture/images/volleyball_poster.png",
    "date": "2026-01-13 19:00",
    "venue": "인천 계양체육관",
    "link": "https://kovo.co.kr/tickets/single",
    "region": "incheon",
    "genre": "volleyball"
  },
  {
    "id": "kovo_20260108_JUNG KWAN JANG_PEPPER SAVINGS BANK",
    "title": "[배구] JUNG KWAN JANG vs PEPPER SAVINGS BANK",
    "image": "/culture/images/volleyball_poster.png",
    "date": "2026-01-08 11:00",
    "venue": "01.13(화) 19:00",
    "link": "https://kovo.co.kr/tickets/single",
    "region": "etc",
    "genre": "volleyball"
  },
  {
    "id": "kovo_20260113_JUNG KWAN JANG_PEPPER SAVINGS BANK",
    "title": "[배구] JUNG KWAN JANG vs PEPPER SAVINGS BANK",
    "image": "/culture/images/volleyball_poster.png",
    "date": "2026-01-13 19:00",
    "venue": "대전 충무체육관",
    "link": "https://kovo.co.kr/tickets/single",
    "region": "etc",
    "genre": "volleyball"
  },
  {
    "id": "kovo_20260108_HEUNGKUK PINKSPIDERS_KOREA EXPRESSWAY",
    "title": "[배구] HEUNGKUK PINKSPIDERS vs KOREA EXPRESSWAY",
    "image": "/culture/images/volleyball_poster.png",
    "date": "2026-01-08 11:00",
    "venue": "01.14(수) 19:00",
    "link": "https://kovo.co.kr/tickets/single",
    "region": "etc",
    "genre": "volleyball"
  },
  {
    "id": "kovo_20260114_HEUNGKUK PINKSPIDERS_KOREA EXPRESSWAY",
    "title": "[배구] HEUNGKUK PINKSPIDERS vs KOREA EXPRESSWAY",
    "image": "/culture/images/volleyball_poster.png",
    "date": "2026-01-14 19:00",
    "venue": "인천 삼산월드체육관",
    "link": "https://kovo.co.kr/tickets/single",
    "region": "incheon",
    "genre": "volleyball"
  },
  {
    "id": "kovo_20260109_HYUNDAI CAPITAL_SAMSUNG BLUEFANGS",
    "title": "[배구] HYUNDAI CAPITAL vs SAMSUNG BLUEFANGS",
    "image": "/culture/images/volleyball_poster.png",
    "date": "2026-01-09 11:00",
    "venue": "01.14(수) 19:00",
    "link": "https://kovo.co.kr/tickets/single",
    "region": "etc",
    "genre": "volleyball"
  },
  {
    "id": "kovo_20260114_HYUNDAI CAPITAL_SAMSUNG BLUEFANGS",
    "title": "[배구] HYUNDAI CAPITAL vs SAMSUNG BLUEFANGS",
    "image": "/culture/images/volleyball_poster.png",
    "date": "2026-01-14 19:00",
    "venue": "천안 유관순체육관",
    "link": "https://kovo.co.kr/tickets/single",
    "region": "etc",
    "genre": "volleyball"
  },
  {
    "id": "kovo_20260109_GS CALTEX_INDUSTRIAL BANK OF KOREA",
    "title": "[배구] GS CALTEX vs INDUSTRIAL BANK OF KOREA",
    "image": "/culture/images/volleyball_poster.png",
    "date": "2026-01-09 11:00",
    "venue": "01.15(목) 19:00",
    "link": "https://kovo.co.kr/tickets/single",
    "region": "etc",
    "genre": "volleyball"
  },
  {
    "id": "kovo_20260115_GS CALTEX_INDUSTRIAL BANK OF KOREA",
    "title": "[배구] GS CALTEX vs INDUSTRIAL BANK OF KOREA",
    "image": "/culture/images/volleyball_poster.png",
    "date": "2026-01-15 19:00",
    "venue": "장충체육관",
    "link": "https://kovo.co.kr/tickets/single",
    "region": "seoul",
    "genre": "volleyball"
  },
  {
    "id": "kovo_20260110_KEPCO_WOORICARD",
    "title": "[배구] KEPCO vs WOORICARD",
    "image": "/culture/images/volleyball_poster.png",
    "date": "2026-01-10 15:00",
    "venue": "01.15(목) 19:00",
    "link": "https://kovo.co.kr/tickets/single",
    "region": "etc",
    "genre": "volleyball"
  },
  {
    "id": "kovo_20260115_KEPCO_WOORICARD",
    "title": "[배구] KEPCO vs WOORICARD",
    "image": "/culture/images/volleyball_poster.png",
    "date": "2026-01-15 19:00",
    "venue": "수원 실내체육관",
    "link": "https://kovo.co.kr/tickets/single",
    "region": "gyeonggi",
    "genre": "volleyball"
  },
  {
    "id": "kovo_20260110_KB STARS_KOREAN AIR",
    "title": "[배구] KB STARS vs KOREAN AIR",
    "image": "/culture/images/volleyball_poster.png",
    "date": "2026-01-10 11:00",
    "venue": "01.16(금) 19:00",
    "link": "https://kovo.co.kr/tickets/single",
    "region": "etc",
    "genre": "volleyball"
  },
  {
    "id": "kovo_20260116_KB STARS_KOREAN AIR",
    "title": "[배구] KB STARS vs KOREAN AIR",
    "image": "/culture/images/volleyball_poster.png",
    "date": "2026-01-16 19:00",
    "venue": "의정부 경민대학교 기념관(체육관)",
    "link": "https://kovo.co.kr/tickets/single",
    "region": "gyeonggi",
    "genre": "volleyball"
  },
  {
    "id": "kovo_20260111_HYUNDAI E&C_JUNG KWAN JANG",
    "title": "[배구] HYUNDAI E&C vs JUNG KWAN JANG",
    "image": "/culture/images/volleyball_poster.png",
    "date": "2026-01-11 11:00",
    "venue": "01.16(금) 19:00",
    "link": "https://kovo.co.kr/tickets/single",
    "region": "etc",
    "genre": "volleyball"
  },
  {
    "id": "kovo_20260116_HYUNDAI E&C_JUNG KWAN JANG",
    "title": "[배구] HYUNDAI E&C vs JUNG KWAN JANG",
    "image": "/culture/images/volleyball_poster.png",
    "date": "2026-01-16 19:00",
    "venue": "수원실내체육관",
    "link": "https://kovo.co.kr/tickets/single",
    "region": "gyeonggi",
    "genre": "volleyball"
  },
  {
    "id": "kovo_20260111_OK SAVINGS BANK_SAMSUNG BLUEFANGS",
    "title": "[배구] OK SAVINGS BANK vs SAMSUNG BLUEFANGS",
    "image": "/culture/images/volleyball_poster.png",
    "date": "2026-01-11 11:00",
    "venue": "01.17(토) 14:00",
    "link": "https://kovo.co.kr/tickets/single",
    "region": "etc",
    "genre": "volleyball"
  },
  {
    "id": "kovo_20260117_OK SAVINGS BANK_SAMSUNG BLUEFANGS",
    "title": "[배구] OK SAVINGS BANK vs SAMSUNG BLUEFANGS",
    "image": "/culture/images/volleyball_poster.png",
    "date": "2026-01-17 14:00",
    "venue": "부산강서실내체육관",
    "link": "https://kovo.co.kr/tickets/single",
    "region": "etc",
    "genre": "volleyball"
  },
  {
    "id": "kovo_20260112_PEPPER SAVINGS BANK_KOREA EXPRESSWAY",
    "title": "[배구] PEPPER SAVINGS BANK vs KOREA EXPRESSWAY",
    "image": "/culture/images/volleyball_poster.png",
    "date": "2026-01-12 11:00",
    "venue": "01.17(토) 16:00",
    "link": "https://kovo.co.kr/tickets/single",
    "region": "etc",
    "genre": "volleyball"
  },
  {
    "id": "kovo_20260117_PEPPER SAVINGS BANK_KOREA EXPRESSWAY",
    "title": "[배구] PEPPER SAVINGS BANK vs KOREA EXPRESSWAY",
    "image": "/culture/images/volleyball_poster.png",
    "date": "2026-01-17 16:00",
    "venue": "페퍼스타디움",
    "link": "https://kovo.co.kr/tickets/single",
    "region": "etc",
    "genre": "volleyball"
  },
  {
    "id": "kovo_20260112_WOORICARD_HYUNDAI CAPITAL",
    "title": "[배구] WOORICARD vs HYUNDAI CAPITAL",
    "image": "/culture/images/volleyball_poster.png",
    "date": "2026-01-12 11:00",
    "venue": "01.18(일) 14:00",
    "link": "https://kovo.co.kr/tickets/single",
    "region": "etc",
    "genre": "volleyball"
  },
  {
    "id": "kovo_20260118_WOORICARD_HYUNDAI CAPITAL",
    "title": "[배구] WOORICARD vs HYUNDAI CAPITAL",
    "image": "/culture/images/volleyball_poster.png",
    "date": "2026-01-18 14:00",
    "venue": "장충체육관",
    "link": "https://kovo.co.kr/tickets/single",
    "region": "seoul",
    "genre": "volleyball"
  },
  {
    "id": "kovo_20260113_INDUSTRIAL BANK OF KOREA_HEUNGKUK PINKSPIDERS",
    "title": "[배구] INDUSTRIAL BANK OF KOREA vs HEUNGKUK PINKSPIDERS",
    "image": "/culture/images/volleyball_poster.png",
    "date": "2026-01-13 11:00",
    "venue": "01.18(일) 16:00",
    "link": "https://kovo.co.kr/tickets/single",
    "region": "etc",
    "genre": "volleyball"
  },
  {
    "id": "kovo_20260118_INDUSTRIAL BANK OF KOREA_HEUNGKUK PINKSPIDERS",
    "title": "[배구] INDUSTRIAL BANK OF KOREA vs HEUNGKUK PINKSPIDERS",
    "image": "/culture/images/volleyball_poster.png",
    "date": "2026-01-18 16:00",
    "venue": "화성종합경기타운 실내체육관",
    "link": "https://kovo.co.kr/tickets/single",
    "region": "gyeonggi",
    "genre": "volleyball"
  }
]